autoagents_graph/__init__.py
autoagents_graph/engine/__init__.py
autoagents_graph/engine/agentify/__init__.py
autoagents_graph/engine/agentify/api/graph_api.py
autoagents_graph/engine/agentify/models/__init__.py
autoagents_graph/engine/agentify/models/graph_types.py
autoagents_graph/engine/agentify/services/__init__.py
autoagents_graph/engine/agentify/services/agentify_graph.py
autoagents_graph/engine/agentify/services/agentify_parser.py
autoagents_graph/engine/agentify/services/node_registry.py
autoagents_graph/engine/agentify/utils/__init__.py
autoagents_graph/engine/agentify/utils/data_converter.py
autoagents_graph/engine/agentify/utils/edge_validator.py
autoagents_graph/engine/agentify/utils/graph_processor.py
autoagents_graph/engine/agentify/utils/node_builder.py
autoagents_graph/engine/agentify/utils/node_validator.py
autoagents_graph/engine/agentify/utils/state_converter.py
autoagents_graph/engine/agentify/utils/template_processor.py
autoagents_graph/engine/comfyui/__init__.py
autoagents_graph/engine/comfyui/models/__init__.py
autoagents_graph/engine/comfyui/services/__init__.py
autoagents_graph/engine/comfyui/utils/__init__.py
autoagents_graph/engine/dify/__init__.py
autoagents_graph/engine/dify/api/__init__.py
autoagents_graph/engine/dify/api/dify_api.py
autoagents_graph/engine/dify/models/__init__.py
autoagents_graph/engine/dify/models/dify_types.py
autoagents_graph/engine/dify/services/__init__.py
autoagents_graph/engine/dify/services/dify_graph.py
autoagents_graph/engine/dify/services/dify_parser.py
autoagents_graph/engine/n8n/__init__.py
autoagents_graph/engine/n8n/models/__init__.py
autoagents_graph/engine/n8n/services/__init__.py
autoagents_graph/engine/n8n/utils/__init__.py
autoagents_graph/prompt/agentify.md
autoagents_graph/prompt/comfyui.md
autoagents_graph/prompt/dify.md
autoagents_graph/prompt/n8n.md
autoagents_graph/services/__init__.py
autoagents_graph/services/config.py
autoagents_graph/services/nl2workflow.py
autoagents_graph-0.1.13.dist-info/METADATA
autoagents_graph-0.1.13.dist-info/WHEEL
autoagents_graph-0.1.13.dist-info/RECORD
