Metadata-Version: 2.4
Name: autoagents-graph
Version: 0.1.13
Summary: The AI Workflow Cross-Platform Engine
Author-email: Hehua Fan <forhheart5532@gmail.com>
License: MIT
Keywords: ai,automation,graph,llm,workflow
Classifier: Development Status :: 3 - Alpha
Classifier: Intended Audience :: Developers
Classifier: License :: OSI Approved :: MIT License
Classifier: Programming Language :: Python :: 3
Classifier: Programming Language :: Python :: 3.11
Classifier: Programming Language :: Python :: 3.12
Classifier: Topic :: Scientific/Engineering :: Artificial Intelligence
Classifier: Topic :: Software Development :: Libraries :: Python Modules
Requires-Python: >=3.9
Requires-Dist: pydantic>=2.11.7
Requires-Dist: pyyaml>=6.0
Requires-Dist: requests>=2.32.4
